watchpoint/__init__.py
watchpoint/api.py
watchpoint/conditions.py
watchpoint/core.py
watchpoint/exceptions.py
watchpoint-0.1.0.dist-info/licenses/LICENSE
watchpoint-0.1.0.dist-info/METADATA
watchpoint-0.1.0.dist-info/WHEEL
watchpoint-0.1.0.dist-info/top_level.txt
watchpoint-0.1.0.dist-info/RECORD
