Metadata-Version: 2.4
Name: watchpoint
Version: 0.1.0
Summary: A lightweight Python utility for running an action when a specific condition is met.
Author-email: Your Name <your.email@example.com>
License: MIT
Classifier: Intended Audience :: Science/Research
Classifier: License :: OSI Approved :: MIT License
Classifier: Operating System :: OS Independent
Classifier: Programming Language :: Python :: 3
Classifier: Programming Language :: Python :: 3.9
Classifier: Programming Language :: Python :: 3.10
Classifier: Programming Language :: Python :: 3.11
Classifier: Programming Language :: Python :: 3.12
Classifier: Programming Language :: Python :: 3.13
Requires-Python: <4.0,>=3.9
License-File: LICENSE
Provides-Extra: dev
Requires-Dist: pytest<9.0.0,>=8.0.0; extra == "dev"
Requires-Dist: black<26.0.0,>=24.0.0; extra == "dev"
Requires-Dist: isort<7.0.0,>=5.13.0; extra == "dev"
Requires-Dist: mypy<2.0.0,>=1.14.0; extra == "dev"
Requires-Dist: flake8<8.0.0,>=7.0.0; extra == "dev"
Requires-Dist: pre-commit<5.0.0,>=3.0.0; extra == "dev"
Requires-Dist: tox<4.29.0,>=4.24.0; extra == "dev"
Dynamic: license-file
